{
  "id": "ab9e8cfc-426a-4d3a-90eb-923ac49d488f",
  "title": "E2E Kitchen 1771933025893",
  "status": "draft",
  "version": 2,
  "customer_name": "E2E Customer",
  "customer_email": "customer@example.com",
  "customer_phone": "555-0101",
  "job_address": "123 Demo Street",
  "estimate_markup_pct": "7.2500",
  "tax_rate_pct": "8.5000",
  "subtotal": "1305.7400",
  "tax": "110.9900",
  "total": "1416.7100",
  "updated_at": "2026-02-24T11:37:08.146967",
  "line_items": [
    {
      "id": "d71384b5-4d49-4ad6-89f1-67994c3ca71f",
      "estimate_id": "ab9e8cfc-426a-4d3a-90eb-923ac49d488f",
      "sort_order": 0,
      "group_name": "Phase-1",
      "item_name": "Custom Tile Install",
      "quantity": "3.0000",
      "unit_price": "47.4700",
      "item_markup_pct": "11.0000",
      "discount_value": "5.0000",
      "discount_is_percent": true,
      "labor_hours": "1.5000",
      "labor_rate": "82.5000",
      "total_price": "309.0200"
    },
    {
      "id": "f5d32462-f0dd-4172-827b-e03de72f70d0",
      "estimate_id": "ab9e8cfc-426a-4d3a-90eb-923ac49d488f",
      "sort_order": 0,
      "group_name": "Phase-1",
      "item_name": "Custom Tile Install",
      "quantity": "3.0000",
      "unit_price": "47.4700",
      "item_markup_pct": "11.0000",
      "discount_value": "0.0000",
      "discount_is_percent": false,
      "labor_hours": "1.5000",
      "labor_rate": "82.5000",
      "total_price": "318.2100"
    },
    {
      "id": "0fed860b-3c3d-48fd-9553-7c92a772b373",
      "estimate_id": "ab9e8cfc-426a-4d3a-90eb-923ac49d488f",
      "sort_order": 1,
      "group_name": "Phase-1",
      "item_name": "Paint Walls",
      "quantity": "4.0000",
      "unit_price": "18.5000",
      "item_markup_pct": "11.0000",
      "discount_value": "5.0000",
      "discount_is_percent": true,
      "labor_hours": "1.5000",
      "labor_rate": "82.5000",
      "total_price": "225.0700"
    },
    {
      "id": "686f829f-5f50-4b27-9900-e6a75ded6d95",
      "estimate_id": "ab9e8cfc-426a-4d3a-90eb-923ac49d488f",
      "sort_order": 1,
      "group_name": "Phase-1",
      "item_name": "Paint Walls",
      "quantity": "4.0000",
      "unit_price": "18.5000",
      "item_markup_pct": "11.0000",
      "discount_value": "0.0000",
      "discount_is_percent": false,
      "labor_hours": "1.5000",
      "labor_rate": "82.5000",
      "total_price": "229.8500"
    },
    {
      "id": "cf4c09ea-15c6-412c-8765-62c3b04c0cba",
      "estimate_id": "ab9e8cfc-426a-4d3a-90eb-923ac49d488f",
      "sort_order": 4,
      "group_name": "Phase-1",
      "item_name": "Countertop Install",
      "quantity": "1.0000",
      "unit_price": "85.0000",
      "item_markup_pct": "12.0000",
      "discount_value": "0.0000",
      "discount_is_percent": false,
      "labor_hours": "2.5000",
      "labor_rate": "82.5000",
      "total_price": "334.5600"
    }
  ]
}